vesper/api/__init__.cpython-38-x86_64-linux-gnu.so
vesper/api/camera_pb2.cpython-38-x86_64-linux-gnu.so
vesper/api/common_pb2.cpython-38-x86_64-linux-gnu.so
vesper/api/control_pb2.cpython-38-x86_64-linux-gnu.so
vesper/api/data_pb2.cpython-38-x86_64-linux-gnu.so
vesper/api/dynamics_pb2.cpython-38-x86_64-linux-gnu.so
vesper/api/effector_pb2.cpython-38-x86_64-linux-gnu.so
vesper/api/execution_pb2.cpython-38-x86_64-linux-gnu.so
vesper/api/fiducial_pb2.cpython-38-x86_64-linux-gnu.so
vesper/api/image_pb2.cpython-38-x86_64-linux-gnu.so
vesper/api/item_pb2.cpython-38-x86_64-linux-gnu.so
vesper/api/linkage_pb2.cpython-38-x86_64-linux-gnu.so
vesper/api/material_pb2.cpython-38-x86_64-linux-gnu.so
vesper/api/math_pb2.cpython-38-x86_64-linux-gnu.so
vesper/api/motion_pb2.cpython-38-x86_64-linux-gnu.so
vesper/api/perception_pb2.cpython-38-x86_64-linux-gnu.so
vesper/api/planning_pb2.cpython-38-x86_64-linux-gnu.so
vesper/api/probability_pb2.cpython-38-x86_64-linux-gnu.so
vesper/api/project_pb2.cpython-38-x86_64-linux-gnu.so
vesper/api/robot_pb2.cpython-38-x86_64-linux-gnu.so
vesper/api/service_pb2.cpython-38-x86_64-linux-gnu.so
vesper/api/service_pb2_grpc.cpython-38-x86_64-linux-gnu.so
vesper/api/shape_pb2.cpython-38-x86_64-linux-gnu.so
vesper/api/simulation_pb2.cpython-38-x86_64-linux-gnu.so
vesper/api/system_pb2.cpython-38-x86_64-linux-gnu.so
vesper/api/task_pb2.cpython-38-x86_64-linux-gnu.so
vesper/api/tool_pb2.cpython-38-x86_64-linux-gnu.so
vesper/api/training_pb2.cpython-38-x86_64-linux-gnu.so
vesper/api/trajectory_pb2.cpython-38-x86_64-linux-gnu.so
vesper/api/variable_pb2.cpython-38-x86_64-linux-gnu.so
vesper/api/workspace_pb2.cpython-38-x86_64-linux-gnu.so
vesper_api-0.8.6.dist-info/LICENCE
vesper_api-0.8.6.dist-info/METADATA
vesper_api-0.8.6.dist-info/WHEEL
vesper_api-0.8.6.dist-info/top_level.txt
vesper_api-0.8.6.dist-info/RECORD
