Metadata-Version: 2.1
Name: vesper-api
Version: 0.8.6
Summary: Vesper API bindings
Author: Parker Owan
License-File: LICENCE
Requires-Dist: grpcio (==1.47)
Requires-Dist: grpcio-tools (==1.47)
